gamer3514/__init__.py
gamer3514/api.py
gamer3514/randomstuff.py
gamer3514/utils.py
gamer3514-0.1.dist-info/LICENSE
gamer3514-0.1.dist-info/METADATA
gamer3514-0.1.dist-info/WHEEL
gamer3514-0.1.dist-info/top_level.txt
gamer3514-0.1.dist-info/RECORD
