Metadata-Version: 2.1
Name: gamer3514
Version: 0.1
Summary: A small package that does stuff
Author-email: Gamer3514 <gamer@sillydev.co.uk>
Project-URL: Homepage, https://github.com/thegamer3514/gamer3514
Project-URL: Bug Tracker, https://github.com/thegamer3514/gamer3514/issues
Classifier: Programming Language :: Python :: 3
Classifier: License :: OSI Approved :: MIT License
Classifier: Operating System :: OS Independent
Requires-Python: >=3.7
License-File: LICENSE
